celluloid.py
celluloid-0.2.0.dist-info/LICENSE
celluloid-0.2.0.dist-info/WHEEL
celluloid-0.2.0.dist-info/METADATA
celluloid-0.2.0.dist-info/RECORD
